Workbook

Sheet Cover
A1: Financial Model: Aurora Retail Co.
A2: Prepared with Finance Studio on 10/29/2026
A3: Blue = input you can change · Green = linked to Historicals · Black = formula
A5: Source data | B5: Aurora Retail Co. · 2020–2024 (5 periods)
A7: Contents
A8: Sheet | B8: What it contains
A9: Historicals | B9: Your uploaded financial statements (the source for linked figures)
A10: Ratios | B10: Ratio analysis linked to Historicals
A12: How to use this model
A13: Input | B13: Blue cells are inputs. Change them and every formula updates.
A14: Linked | B14: Green cells link to the Historicals sheet.
A15: Formula | B15: Black cells are formulas. Avoid typing over them.
A16: Output | B16: Shaded cells are key outputs.
A18: Models are planning tools based on the data and assumptions provided. They are not investment advice.

Sheet Historicals
A1: Historical Financial Statements
A2: Aurora Retail Co. · as uploaded
A3: Blue = input you can change · Green = linked to Historicals · Black = formula
A5: Financial statements
A6: Line item | B6: 2020 | C6: 2021 | D6: 2022 | E6: 2023 | F6: 2024
A7: Revenue | B7: 8200000 | C7: 9100000 | D7: 10400000 | E7: 11800000 | F7: 13100000
A8: Cost of Goods Sold | B8: 4900000 | C8: 5400000 | D8: 6100000 | E8: 6800000 | F8: 7500000
A9: Gross Profit | B9: 3300000 | C9: 3700000 | D9: 4300000 | E9: 5000000 | F9: 5600000
A10: Operating Expenses | B10: 1800000 | C10: 1950000 | D10: 2150000 | E10: 2400000 | F10: 2600000
A11: EBITDA | B11: 1500000 | C11: 1750000 | D11: 2150000 | E11: 2600000 | F11: 3000000
A12: D&A | B12: 300000 | C12: 330000 | D12: 360000 | E12: 400000 | F12: 440000
A13: EBIT | B13: 1200000 | C13: 1420000 | D13: 1790000 | E13: 2200000 | F13: 2560000
A14: Interest Expense | B14: 180000 | C14: 170000 | D14: 160000 | E14: 150000 | F14: 140000
A15: Net Income | B15: 765000 | C15: 937500 | D15: 1222500 | E15: 1537500 | F15: 1815000
A16: Cash | B16: 900000 | C16: 1100000 | D16: 1400000 | E16: 1800000 | F16: 2300000
A17: Current Assets | B17: 3100000 | C17: 3500000 | D17: 4000000 | E17: 4600000 | F17: 5300000
A18: Total Assets | B18: 9500000 | C18: 10300000 | D18: 11400000 | E18: 12600000 | F18: 14000000
... A24: Operating Cash Flow | B24: 1200000 | C24: 1400000 | D24: 1700000 | E24: 2000000 | F24: 2400000

Sheet Ratios
A1: Ratio Analysis
A2: Aurora Retail Co. · calculated from Historicals
A3: Blue = input you can change · Green = linked to Historicals · Black = formula
A5: Ratios by year
A6: Ratio | B6: 2020 | C6: 2021 | D6: 2022 | E6: 2023 | F6: 2024
A7: Revenue growth | C7: =IFERROR(Historicals!C7/Historicals!B7-1,"") -> 0.1097561 | D7: =IFERROR(Historicals!D7/Historicals!C7-1,"") -> 0.14285714 | E7: =IFERROR(Historicals!E7/Historicals!D7-1,"") -> 0.13461538 | F7: =IFERROR(Historicals!F7/Historicals!E7-1,"") -> 0.11016949
A8: Gross margin | B8: =IFERROR(Historicals!B9/Historicals!B7,"") -> 0.40243902 | C8: =IFERROR(Historicals!C9/Historicals!C7,"") -> 0.40659341 | D8: =IFERROR(Historicals!D9/Historicals!D7,"") -> 0.41346154 | E8: =IFERROR(Historicals!E9/Historicals!E7,"") -> 0.42372881 | F8: =IFERROR(Historicals!F9/Historicals!F7,"") -> 0.42748092
A9: EBITDA margin | B9: =IFERROR(Historicals!B11/Historicals!B7,"") -> 0.18292683 | C9: =IFERROR(Historicals!C11/Historicals!C7,"") -> 0.19230769 | D9: =IFERROR(Historicals!D11/Historicals!D7,"") -> 0.20673077 | E9: =IFERROR(Historicals!E11/Historicals!E7,"") -> 0.22033898 | F9: =IFERROR(Historicals!F11/Historicals!F7,"") -> 0.22900763
A10: Net margin | B10: =IFERROR(Historicals!B15/Historicals!B7,"") -> 0.093292683 | C10: =IFERROR(Historicals!C15/Historicals!C7,"") -> 0.10302198 | D10: =IFERROR(Historicals!D15/Historicals!D7,"") -> 0.11754808 | E10: =IFERROR(Historicals!E15/Historicals!E7,"") -> 0.13029661 | F10: =IFERROR(Historicals!F15/Historicals!F7,"") -> 0.13854962
A11: Current ratio | B11: =IFERROR(Historicals!B17/Historicals!B19,"") -> 1.6315789 | C11: =IFERROR(Historicals!C17/Historicals!C19,"") -> 1.75 | D11: =IFERROR(Historicals!D17/Historicals!D19,"") -> 1.8181818 | E11: =IFERROR(Historicals!E17/Historicals!E19,"") -> 1.9166667 | F11: =IFERROR(Historicals!F17/Historicals!F19,"") -> 2.0384615
A12: Debt / Equity | B12: =IFERROR(Historicals!B21/Historicals!B22,"") -> 0.73170732 | C12: =IFERROR(Historicals!C21/Historicals!C22,"") -> 0.57142857 | D12: =IFERROR(Historicals!D21/Historicals!D22,"") -> 0.44067797 | E12: =IFERROR(Historicals!E21/Historicals!E22,"") -> 0.34285714 | F12: =IFERROR(Historicals!F21/Historicals!F22,"") -> 0.26829268
A13: Debt / EBITDA | B13: =IFERROR(Historicals!B21/Historicals!B11,"") -> 2 | C13: =IFERROR(Historicals!C21/Historicals!C11,"") -> 1.6 | D13: =IFERROR(Historicals!D21/Historicals!D11,"") -> 1.2093023 | E13: =IFERROR(Historicals!E21/Historicals!E11,"") -> 0.92307692 | F13: =IFERROR(Historicals!F21/Historicals!F11,"") -> 0.73333333
A14: Interest coverage (EBIT / interest) | B14: =IFERROR(Historicals!B13/Historicals!B14,"") -> 6.6666667 | C14: =IFERROR(Historicals!C13/Historicals!C14,"") -> 8.3529412 | D14: =IFERROR(Historicals!D13/Historicals!D14,"") -> 11.1875 | E14: =IFERROR(Historicals!E13/Historicals!E14,"") -> 14.666667 | F14: =IFERROR(Historicals!F13/Historicals!F14,"") -> 18.285714
A15: Return on assets | B15: =IFERROR(Historicals!B15/Historicals!B18,"") -> 0.080526316 | C15: =IFERROR(Historicals!C15/Historicals!C18,"") -> 0.091019417 | D15: =IFERROR(Historicals!D15/Historicals!D18,"") -> 0.10723684 | E15: =IFERROR(Historicals!E15/Historicals!E18,"") -> 0.12202381 | F15: =IFERROR(Historicals!F15/Historicals!F18,"") -> 0.12964286
A16: Return on equity | B16: =IFERROR(Historicals!B15/Historicals!B22,"") -> 0.18658537 | C16: =IFERROR(Historicals!C15/Historicals!C22,"") -> 0.19132653 | D16: =IFERROR(Historicals!D15/Historicals!D22,"") -> 0.20720339 | E16: =IFERROR(Historicals!E15/Historicals!E22,"") -> 0.21964286 | F16: =IFERROR(Historicals!F15/Historicals!F22,"") -> 0.22134146
A17: Cash conversion (OCF / net income) | B17: =IFERROR(Historicals!B24/Historicals!B15,"") -> 1.5686275 | C17: =IFERROR(Historicals!C24/Historicals!C15,"") -> 1.4933333 | D17: =IFERROR(Historicals!D24/Historicals!D15,"") -> 1.390593 | E17: =IFERROR(Historicals!E24/Historicals!E15,"") -> 1.300813 | F17: =IFERROR(Historicals!F24/Historicals!F15,"") -> 1.322314
